KratosDelaunayMeshingApplication.libs/libKratosDelaunayMeshingCore-5292dbf9.so
KratosDelaunayMeshingApplication-9.1.3.dist-info/METADATA
KratosDelaunayMeshingApplication-9.1.3.dist-info/WHEEL
KratosDelaunayMeshingApplication-9.1.3.dist-info/top_level.txt
KratosDelaunayMeshingApplication-9.1.3.dist-info/RECORD
KratosMultiphysics/DelaunayMeshingApplication/domain_utilities.py
KratosMultiphysics/DelaunayMeshingApplication/meshing_strategy.py
KratosMultiphysics/DelaunayMeshingApplication/constant_rotation_process.py
KratosMultiphysics/DelaunayMeshingApplication/mesher.py
KratosMultiphysics/DelaunayMeshingApplication/transfer_mesher.py
KratosMultiphysics/DelaunayMeshingApplication/post_refining_mesher.py
KratosMultiphysics/DelaunayMeshingApplication/remesh_domains_process.py
KratosMultiphysics/DelaunayMeshingApplication/pre_refining_mesher.py
KratosMultiphysics/DelaunayMeshingApplication/meshing_domain.py
KratosMultiphysics/DelaunayMeshingApplication/reconnect_mesher.py
KratosMultiphysics/DelaunayMeshingApplication/__init__.py
KratosMultiphysics/.libs/KratosDelaunayMeshingApplication.cpython-36m-x86_64-linux-gnu.so
